aziraclient/__init__.py
aziraclient/auth/__init__.py
aziraclient/auth/auth_client.py
aziraclient/connector/__init__.py
aziraclient/connector/connection.py
aziraclient/message_bus/__init__.py
aziraclient/message_bus/message_bus_tester.py
aziraclient/subscription/__init__.py
aziraclient/subscription/subscription.py
tests/__init__.py
tests/test_auth.py
tests/test_message_bus.py
tests/test_subscription.py
aziraclient-0.1.5.dist-info/LICENSE
aziraclient-0.1.5.dist-info/METADATA
aziraclient-0.1.5.dist-info/WHEEL
aziraclient-0.1.5.dist-info/top_level.txt
aziraclient-0.1.5.dist-info/RECORD
