Metadata-Version: 2.1
Name: aziraclient
Version: 0.1.5
Summary: A library built for azira application to make it easier for users to subscribe to crypto tokens and continuously receive data in near real-time
Home-page: https://github.com/manny-uncharted/aziraclient
Author: Emmanuel Akanji
Author-email: omoebun52@gmail.com
Classifier: Programming Language :: Python :: 3
Classifier: License :: OSI Approved :: MIT License
Classifier: Operating System :: OS Independent
Requires-Python: >=3.6
License-File: LICENSE
Requires-Dist: amqp ==5.2.0
Requires-Dist: annotated-types ==0.6.0
Requires-Dist: anyio ==3.7.1
Requires-Dist: async-timeout ==4.0.3
Requires-Dist: fastapi ==0.104.1
Requires-Dist: fastapi-socketio ==0.0.10
Requires-Dist: httpcore ==1.0.1
Requires-Dist: httpx ==0.25.1
Requires-Dist: idna ==3.4
Requires-Dist: iniconfig ==2.0.0
Requires-Dist: iso8601 ==2.1.0
Requires-Dist: jwt ==1.3.1
Requires-Dist: kombu ==5.3.3
Requires-Dist: Mako ==1.3.0
Requires-Dist: pytest ==7.4.3
Requires-Dist: python-engineio ==4.8.0
Requires-Dist: python-socketio ==5.10.0
Requires-Dist: requests ==2.31.0
Requires-Dist: websockets ==12.0
Requires-Dist: zmq ==0.0.0
